moraine/__init__.py
moraine/_modidx.py
moraine/calamp.py
moraine/chunk_.py
moraine/co.py
moraine/coord_.py
moraine/dl.py
moraine/gamma_.py
moraine/pc.py
moraine/pl.py
moraine/plot.py
moraine/pqm.py
moraine/ps.py
moraine/pu.py
moraine/rtree.py
moraine/shp.py
moraine/tnet.py
moraine/utils_.py
moraine/cli/__init__.py
moraine/cli/co.py
moraine/cli/dask_.py
moraine/cli/dl.py
moraine/cli/load.py
moraine/cli/logging.py
moraine/cli/math.py
moraine/cli/pc.py
moraine/cli/pl.py
moraine/cli/plot.py
moraine/cli/pqm.py
moraine/cli/ps.py
moraine/cli/pu.py
moraine/cli/shp.py
moraine/cli/transform.py
moraine/cli/utils_.py
moraine/dl_model/__init__.py
moraine-0.8.5.dist-info/licenses/LICENSE
moraine-0.8.5.dist-info/METADATA
moraine-0.8.5.dist-info/WHEEL
moraine-0.8.5.dist-info/entry_points.txt
moraine-0.8.5.dist-info/top_level.txt
moraine-0.8.5.dist-info/RECORD
