Metadata-Version: 2.4
Name: moraine
Version: 0.8.5
Summary: Modern Radar Interferometry Environment, A simple, stupid InSAR postprocessing tool in big data era
Home-page: https://github.com/kanglcn/moraine
Author: kanglcn
Author-email: kanglcn@gmail.com
License: GNU General Public License v3
Project-URL: Documentation, https://kanglcn.github.io/moraine
Keywords: InSAR PS DS CUDA Deep-learning
Classifier: Development Status :: 3 - Alpha
Classifier: Intended Audience :: Developers
Classifier: Natural Language :: English
Classifier: Programming Language :: Python :: 3.11
Classifier: Programming Language :: Python :: 3.12
Classifier: Programming Language :: Python :: 3.13
Classifier: License :: OSI Approved :: GNU General Public License v3 (GPLv3)
Requires-Python: >=3.11
License-File: LICENSE
Requires-Dist: packaging
Requires-Dist: numpy
Requires-Dist: scipy
Requires-Dist: matplotlib
Requires-Dist: zarr
Requires-Dist: colorcet
Requires-Dist: fastcore
Requires-Dist: toml
Requires-Dist: numba>=0.59
Requires-Dist: numexpr
Requires-Dist: bokeh>=3.4.1
Requires-Dist: holoviews>=1.18.3
Requires-Dist: pyproj>=3.0
Requires-Dist: numcodecs
Requires-Dist: dask[complete]
Requires-Dist: fpsample
Requires-Dist: onnxruntime
Provides-Extra: dev
Requires-Dist: nbdev; extra == "dev"
Requires-Dist: pre-commit; extra == "dev"
Requires-Dist: quarto; extra == "dev"
Dynamic: author
Dynamic: author-email
Dynamic: classifier
Dynamic: description
Dynamic: description-content-type
Dynamic: home-page
Dynamic: keywords
Dynamic: license
Dynamic: license-file
Dynamic: project-url
Dynamic: provides-extra
Dynamic: requires-dist
Dynamic: requires-python
Dynamic: summary
